[{"userProfilePK":81077219,"calendarDate":"2023-06-27","deviceId":3312246524,"updateTimestamp":"2023-06-27T14:56:30.0","sport":"WALKING","subSport":"GENERIC","vo2MaxValue":41.0,"fitnessAge":"21","fitnessAgeDescription":"3","analyzerMethod":5,"maxMet":11.767623901367188,"maxMetCategory":"GENERIC","calibratedData":1},{"userProfilePK":81077219,"calendarDate":"2023-06-27","deviceId":3312246524,"updateTimestamp":"2023-06-27T22:18:02.0","sport":"WALKING","subSport":"GENERIC","vo2MaxValue":41.0,"fitnessAge":"20","fitnessAgeDescription":"3","analyzerMethod":5,"maxMet":11.792922973632812,"maxMetCategory":"GENERIC","calibratedData":1},{"userProfilePK":81077219,"calendarDate":"2023-06-28","deviceId":3312246524,"updateTimestamp":"2023-06-28T16:37:57.0","sport":"WALKING","subSport":"GENERIC","vo2MaxValue":41.0,"fitnessAge":"21","fitnessAgeDescription":"3","analyzerMethod":5,"maxMet":11.76751708984375,"maxMetCategory":"GENERIC","calibratedData":1},{"userProfilePK":81077219,"calendarDate":"2023-06-29","deviceId":3312246524,"updateTimestamp":"2023-06-29T16:32:10.0","sport":"WALKING","subSport":"GENERIC","vo2MaxValue":41.0,"fitnessAge":"21","fitnessAgeDescription":"3","analyzerMethod":5,"maxMet":11.739669799804688,"maxMetCategory":"GENERIC","calibratedData":1},{"userProfilePK":81077219,"calendarDate":"2023-06-30","deviceId":3312246524,"updateTimestamp":"2023-06-30T16:04:12.0","sport":"WALKING","subSport":"GENERIC","vo2MaxValue":41.0,"fitnessAge":"22","fitnessAgeDescription":"3","analyzerMethod":5,"maxMet":11.668853759765625,"maxMetCategory":"GENERIC","calibratedData":1},{"userProfilePK":81077219,"calendarDate":"2023-07-03","deviceId":3312246524,"updateTimestamp":"2023-07-03T17:51:37.0","sport":"WALKING","subSport":"GENERIC","vo2MaxValue":40.0,"fitnessAge":"24","fitnessAgeDescription":"2","analyzerMethod":5,"maxMet":11.372482299804688,"maxMetCategory":"GENERIC","calibratedData":1},{"userProfilePK":81077219,"calendarDate":"2023-07-05","deviceId":3312246524,"updateTimestamp":"2023-07-05T21:16:11.0","sport":"WALKING","subSport":"GENERIC","vo2MaxValue":40.0,"fitnessAge":"24","fitnessAgeDescription":"2","analyzerMethod":5,"maxMet":11.43743896484375,"maxMetCategory":"GENERIC","calibratedData":1},{"userProfilePK":81077219,"calendarDate":"2023-07-06","deviceId":3312246524,"updateTimestamp":"2023-07-06T15:13:49.0","sport":"WALKING","subSport":"GENERIC","vo2MaxValue":40.0,"fitnessAge":"24","fitnessAgeDescription":"2","analyzerMethod":5,"maxMet":11.456497192382812,"maxMetCategory":"GENERIC","calibratedData":1},{"userProfilePK":81077219,"calendarDate":"2023-07-08","deviceId":3312246524,"updateTimestamp":"2023-07-08T20:58:32.0","sport":"WALKING","subSport":"GENERIC","vo2MaxValue":40.0,"fitnessAge":"23","fitnessAgeDescription":"2","analyzerMethod":5,"maxMet":11.499420166015625,"maxMetCategory":"GENERIC","calibratedData":1},{"userProfilePK":81077219,"calendarDate":"2023-07-09","deviceId":3312246524,"updateTimestamp":"2023-07-09T16:55:00.0","sport":"WALKING","subSport":"GENERIC","vo2MaxValue":41.0,"fitnessAge":"22","fitnessAgeDescription":"3","analyzerMethod":5,"maxMet":11.623062133789062,"maxMetCategory":"GENERIC","calibratedData":1},{"userProfilePK":81077219,"calendarDate":"2023-07-09","deviceId":3312246524,"updateTimestamp":"2023-07-10T00:58:10.0","sport":"WALKING","subSport":"GENERIC","vo2MaxValue":41.0,"fitnessAge":"21","fitnessAgeDescription":"3","analyzerMethod":5,"maxMet":11.739288330078125,"maxMetCategory":"GENERIC","calibratedData":1},{"userProfilePK":81077219,"calendarDate":"2023-07-10","deviceId":3312246524,"updateTimestamp":"2023-07-10T16:19:27.0","sport":"WALKING","subSport":"GENERIC","vo2MaxValue":41.0,"fitnessAge":"21","fitnessAgeDescription":"3","analyzerMethod":5,"maxMet":11.702713012695312,"maxMetCategory":"GENERIC","calibratedData":1},{"userProfilePK":81077219,"calendarDate":"2023-07-10","deviceId":3312246524,"updateTimestamp":"2023-07-10T22:18:46.0","sport":"WALKING","subSport":"GENERIC","vo2MaxValue":41.0,"fitnessAge":"21","fitnessAgeDescription":"3","analyzerMethod":5,"maxMet":11.721878051757812,"maxMetCategory":"GENERIC","calibratedData":1},{"userProfilePK":81077219,"calendarDate":"2023-07-10","deviceId":3312246524,"updateTimestamp":"2023-07-11T02:13:38.0","sport":"WALKING","subSport":"GENERIC","vo2MaxValue":41.0,"fitnessAge":"20","fitnessAgeDescription":"3","analyzerMethod":5,"maxMet":11.823486328125,"maxMetCategory":"GENERIC","calibratedData":1},{"userProfilePK":81077219,"calendarDate":"2023-07-12","deviceId":3312246524,"updateTimestamp":"2023-07-12T21:45:53.0","sport":"WALKING","subSport":"GENERIC","vo2MaxValue":41.0,"fitnessAge":"20","fitnessAgeDescription":"3","analyzerMethod":5,"maxMet":11.84185791015625,"maxMetCategory":"GENERIC","calibratedData":1},{"userProfilePK":81077219,"calendarDate":"2023-07-13","deviceId":3312246524,"updateTimestamp":"2023-07-14T03:14:37.0","sport":"WALKING","subSport":"GENERIC","vo2MaxValue":42.0,"fitnessAge":"20","fitnessAgeDescription":"3","analyzerMethod":5,"maxMet":11.910995483398438,"maxMetCategory":"GENERIC","calibratedData":1},{"userProfilePK":81077219,"calendarDate":"2023-07-16","deviceId":3312246524,"updateTimestamp":"2023-07-17T03:00:13.0","sport":"WALKING","subSport":"GENERIC","vo2MaxValue":42.0,"fitnessAge":"20","fitnessAgeDescription":"3","analyzerMethod":5,"maxMet":11.92230224609375,"maxMetCategory":"GENERIC","calibratedData":1},{"userProfilePK":81077219,"calendarDate":"2023-07-17","deviceId":3312246524,"updateTimestamp":"2023-07-17T15:57:06.0","sport":"WALKING","subSport":"GENERIC","vo2MaxValue":41.0,"fitnessAge":"20","fitnessAgeDescription":"3","analyzerMethod":5,"maxMet":11.806610107421875,"maxMetCategory":"GENERIC","calibratedData":1},{"userProfilePK":81077219,"calendarDate":"2023-07-17","deviceId":3312246524,"updateTimestamp":"2023-07-17T19:44:40.0","sport":"WALKING","subSport":"GENERIC","vo2MaxValue":41.0,"fitnessAge":"20","fitnessAgeDescription":"3","analyzerMethod":5,"maxMet":11.856887817382812,"maxMetCategory":"GENERIC","calibratedData":1},{"userProfilePK":81077219,"calendarDate":"2023-07-18","deviceId":3312246524,"updateTimestamp":"2023-07-18T15:31:32.0","sport":"WALKING","subSport":"GENERIC","vo2MaxValue":41.0,"fitnessAge":"20","fitnessAgeDescription":"3","analyzerMethod":5,"maxMet":11.784164428710938,"maxMetCategory":"GENERIC","calibratedData":1},{"userProfilePK":81077219,"calendarDate":"2023-07-18","deviceId":3312246524,"updateTimestamp":"2023-07-19T00:10:52.0","sport":"WALKING","subSport":"GENERIC","vo2MaxValue":42.0,"fitnessAge":"20","fitnessAgeDescription":"3","analyzerMethod":5,"maxMet":11.880813598632812,"maxMetCategory":"GENERIC","calibratedData":1},{"userProfilePK":81077219,"calendarDate":"2023-07-19","deviceId":3312246524,"updateTimestamp":"2023-07-19T15:58:27.0","sport":"WALKING","subSport":"GENERIC","vo2MaxValue":41.0,"fitnessAge":"20","fitnessAgeDescription":"3","analyzerMethod":5,"maxMet":11.851470947265625,"maxMetCategory":"GENERIC","calibratedData":1},{"userProfilePK":81077219,"calendarDate":"2023-07-22","deviceId":3312246524,"updateTimestamp":"2023-07-23T01:47:48.0","sport":"WALKING","subSport":"GENERIC","vo2MaxValue":41.0,"fitnessAge":"20","fitnessAgeDescription":"3","analyzerMethod":5,"maxMet":11.803924560546875,"maxMetCategory":"GENERIC","calibratedData":1},{"userProfilePK":81077219,"calendarDate":"2023-07-22","deviceId":3312246524,"updateTimestamp":"2023-07-23T02:13:47.0","sport":"WALKING","subSport":"GENERIC","vo2MaxValue":41.0,"fitnessAge":"21","fitnessAgeDescription":"3","analyzerMethod":5,"maxMet":11.765411376953125,"maxMetCategory":"GENERIC","calibratedData":1},{"userProfilePK":81077219,"calendarDate":"2023-07-23","deviceId":3312246524,"updateTimestamp":"2023-07-24T01:18:50.0","sport":"WALKING","subSport":"GENERIC","vo2MaxValue":41.0,"fitnessAge":"20","fitnessAgeDescription":"3","analyzerMethod":5,"maxMet":11.8392333984375,"maxMetCategory":"GENERIC","calibratedData":1},{"userProfilePK":81077219,"calendarDate":"2023-07-24","deviceId":3312246524,"updateTimestamp":"2023-07-24T16:50:17.0","sport":"WALKING","subSport":"GENERIC","vo2MaxValue":41.0,"fitnessAge":"20","fitnessAgeDescription":"3","analyzerMethod":5,"maxMet":11.848403930664062,"maxMetCategory":"GENERIC","calibratedData":1},{"userProfilePK":81077219,"calendarDate":"2023-07-24","deviceId":3312246524,"updateTimestamp":"2023-07-25T02:23:39.0","sport":"WALKING","subSport":"GENERIC","vo2MaxValue":42.0,"fitnessAge":"20","fitnessAgeDescription":"3","analyzerMethod":5,"maxMet":11.985504150390625,"maxMetCategory":"GENERIC","calibratedData":1},{"userProfilePK":81077219,"calendarDate":"2023-07-25","deviceId":3312246524,"updateTimestamp":"2023-07-25T16:17:17.0","sport":"WALKING","subSport":"GENERIC","vo2MaxValue":42.0,"fitnessAge":"20","fitnessAgeDescription":"3","analyzerMethod":5,"maxMet":11.913284301757812,"maxMetCategory":"GENERIC","calibratedData":1},{"userProfilePK":81077219,"calendarDate":"2023-07-26","deviceId":3312246524,"updateTimestamp":"2023-07-26T17:30:58.0","sport":"WALKING","subSport":"GENERIC","vo2MaxValue":42.0,"fitnessAge":"20","fitnessAgeDescription":"3","analyzerMethod":5,"maxMet":11.869552612304688,"maxMetCategory":"GENERIC","calibratedData":1},{"userProfilePK":81077219,"calendarDate":"2023-07-29","deviceId":3312246524,"updateTimestamp":"2023-07-30T01:15:23.0","sport":"WALKING","subSport":"GENERIC","vo2MaxValue":42.0,"fitnessAge":"20","fitnessAgeDescription":"3","analyzerMethod":5,"maxMet":11.965927124023438,"maxMetCategory":"GENERIC","calibratedData":1},{"userProfilePK":81077219,"calendarDate":"2023-07-31","deviceId":3312246524,"updateTimestamp":"2023-07-31T16:57:53.0","sport":"WALKING","subSport":"GENERIC","vo2MaxValue":42.0,"fitnessAge":"20","fitnessAgeDescription":"3","analyzerMethod":5,"maxMet":11.9322509765625,"maxMetCategory":"GENERIC","calibratedData":1},{"userProfilePK":81077219,"calendarDate":"2023-08-01","deviceId":3312246524,"updateTimestamp":"2023-08-01T22:05:33.0","sport":"WALKING","subSport":"GENERIC","vo2MaxValue":42.0,"fitnessAge":"20","fitnessAgeDescription":"3","analyzerMethod":5,"maxMet":11.954116821289062,"maxMetCategory":"GENERIC","calibratedData":1},{"userProfilePK":81077219,"calendarDate":"2023-08-03","deviceId":3312246524,"updateTimestamp":"2023-08-03T15:58:15.0","sport":"WALKING","subSport":"GENERIC","vo2MaxValue":41.0,"fitnessAge":"20","fitnessAgeDescription":"3","analyzerMethod":5,"maxMet":11.84716796875,"maxMetCategory":"GENERIC","calibratedData":1},{"userProfilePK":81077219,"calendarDate":"2023-08-05","deviceId":3312246524,"updateTimestamp":"2023-08-05T16:45:34.0","sport":"WALKING","subSport":"GENERIC","vo2MaxValue":42.0,"fitnessAge":"20","fitnessAgeDescription":"3","analyzerMethod":5,"maxMet":11.922073364257812,"maxMetCategory":"GENERIC","calibratedData":1},{"userProfilePK":81077219,"calendarDate":"2023-08-06","deviceId":3312246524,"updateTimestamp":"2023-08-06T18:39:42.0","sport":"WALKING","subSport":"GENERIC","vo2MaxValue":40.0,"fitnessAge":"23","fitnessAgeDescription":"2","analyzerMethod":5,"maxMet":11.4927978515625,"maxMetCategory":"GENERIC","calibratedData":1},{"userProfilePK":81077219,"calendarDate":"2023-08-06","deviceId":3312246524,"updateTimestamp":"2023-08-06T19:40:13.0","sport":"WALKING","subSport":"GENERIC","vo2MaxValue":40.0,"fitnessAge":"23","fitnessAgeDescription":"2","analyzerMethod":5,"maxMet":11.505599975585938,"maxMetCategory":"GENERIC","calibratedData":1},{"userProfilePK":81077219,"calendarDate":"2023-08-07","deviceId":3312246524,"updateTimestamp":"2023-08-08T02:43:50.0","sport":"WALKING","subSport":"GENERIC","vo2MaxValue":41.0,"fitnessAge":"22","fitnessAgeDescription":"3","analyzerMethod":5,"maxMet":11.637802124023438,"maxMetCategory":"GENERIC","calibratedData":1},{"userProfilePK":81077219,"calendarDate":"2023-08-08","deviceId":3312246524,"updateTimestamp":"2023-08-08T17:11:08.0","sport":"WALKING","subSport":"GENERIC","vo2MaxValue":41.0,"fitnessAge":"22","fitnessAgeDescription":"3","analyzerMethod":5,"maxMet":11.631546020507812,"maxMetCategory":"GENERIC","calibratedData":1},{"userProfilePK":81077219,"calendarDate":"2023-08-10","deviceId":3312246524,"updateTimestamp":"2023-08-11T02:02:53.0","sport":"WALKING","subSport":"GENERIC","vo2MaxValue":41.0,"fitnessAge":"21","fitnessAgeDescription":"3","analyzerMethod":5,"maxMet":11.708938598632812,"maxMetCategory":"GENERIC","calibratedData":1},{"userProfilePK":81077219,"calendarDate":"2023-08-12","deviceId":3312246524,"updateTimestamp":"2023-08-12T22:13:04.0","sport":"WALKING","subSport":"GENERIC","vo2MaxValue":41.0,"fitnessAge":"21","fitnessAgeDescription":"3","analyzerMethod":5,"maxMet":11.751602172851562,"maxMetCategory":"GENERIC","calibratedData":1},{"userProfilePK":81077219,"calendarDate":"2023-08-13","deviceId":3312246524,"updateTimestamp":"2023-08-13T19:30:13.0","sport":"WALKING","subSport":"GENERIC","vo2MaxValue":41.0,"fitnessAge":"22","fitnessAgeDescription":"3","analyzerMethod":5,"maxMet":11.588607788085938,"maxMetCategory":"GENERIC","calibratedData":1},{"userProfilePK":81077219,"calendarDate":"2023-08-13","deviceId":3312246524,"updateTimestamp":"2023-08-13T23:07:14.0","sport":"WALKING","subSport":"GENERIC","vo2MaxValue":39.0,"fitnessAge":"25","fitnessAgeDescription":"2","analyzerMethod":5,"maxMet":11.285232543945312,"maxMetCategory":"GENERIC","calibratedData":1},{"userProfilePK":81077219,"calendarDate":"2023-08-16","deviceId":3312246524,"updateTimestamp":"2023-08-16T16:28:03.0","sport":"WALKING","subSport":"GENERIC","vo2MaxValue":39.0,"fitnessAge":"25","fitnessAgeDescription":"2","analyzerMethod":5,"maxMet":11.27642822265625,"maxMetCategory":"GENERIC","calibratedData":1},{"userProfilePK":81077219,"calendarDate":"2023-08-17","deviceId":3312246524,"updateTimestamp":"2023-08-17T22:22:09.0","sport":"WALKING","subSport":"GENERIC","vo2MaxValue":40.0,"fitnessAge":"24","fitnessAgeDescription":"2","analyzerMethod":5,"maxMet":11.37799072265625,"maxMetCategory":"GENERIC","calibratedData":1},{"userProfilePK":81077219,"calendarDate":"2023-08-20","deviceId":3312246524,"updateTimestamp":"2023-08-20T22:11:28.0","sport":"WALKING","subSport":"GENERIC","vo2MaxValue":38.0,"fitnessAge":"29","fitnessAgeDescription":"2","analyzerMethod":5,"maxMet":10.931442260742188,"maxMetCategory":"GENERIC","calibratedData":1},{"userProfilePK":81077219,"calendarDate":"2023-08-21","deviceId":3312246524,"updateTimestamp":"2023-08-21T23:20:39.0","sport":"WALKING","subSport":"GENERIC","vo2MaxValue":39.0,"fitnessAge":"28","fitnessAgeDescription":"2","analyzerMethod":5,"maxMet":11.037857055664062,"maxMetCategory":"GENERIC","calibratedData":1},{"userProfilePK":81077219,"calendarDate":"2023-08-22","deviceId":3312246524,"updateTimestamp":"2023-08-22T21:16:31.0","sport":"WALKING","subSport":"GENERIC","vo2MaxValue":39.0,"fitnessAge":"27","fitnessAgeDescription":"2","analyzerMethod":5,"maxMet":11.114898681640625,"maxMetCategory":"GENERIC","calibratedData":1},{"userProfilePK":81077219,"calendarDate":"2023-08-23","deviceId":3312246524,"updateTimestamp":"2023-08-23T16:32:03.0","sport":"WALKING","subSport":"GENERIC","vo2MaxValue":39.0,"fitnessAge":"27","fitnessAgeDescription":"2","analyzerMethod":5,"maxMet":11.048507690429688,"maxMetCategory":"GENERIC","calibratedData":1},{"userProfilePK":81077219,"calendarDate":"2023-08-23","deviceId":3312246524,"updateTimestamp":"2023-08-23T23:44:30.0","sport":"WALKING","subSport":"GENERIC","vo2MaxValue":39.0,"fitnessAge":"27","fitnessAgeDescription":"2","analyzerMethod":5,"maxMet":11.095672607421875,"maxMetCategory":"GENERIC","calibratedData":1},{"userProfilePK":81077219,"calendarDate":"2023-08-28","deviceId":3312246524,"updateTimestamp":"2023-08-28T15:02:33.0","sport":"WALKING","subSport":"GENERIC","vo2MaxValue":39.0,"fitnessAge":"27","fitnessAgeDescription":"2","analyzerMethod":5,"maxMet":11.138687133789062,"maxMetCategory":"GENERIC","calibratedData":1},{"userProfilePK":81077219,"calendarDate":"2023-08-28","deviceId":3312246524,"updateTimestamp":"2023-08-29T02:23:40.0","sport":"WALKING","subSport":"GENERIC","vo2MaxValue":40.0,"fitnessAge":"25","fitnessAgeDescription":"2","analyzerMethod":5,"maxMet":11.331802368164062,"maxMetCategory":"GENERIC","calibratedData":1},{"userProfilePK":81077219,"calendarDate":"2023-08-30","deviceId":3312246524,"updateTimestamp":"2023-08-30T21:43:14.0","sport":"WALKING","subSport":"GENERIC","vo2MaxValue":40.0,"fitnessAge":"24","fitnessAgeDescription":"2","analyzerMethod":5,"maxMet":11.417922973632812,"maxMetCategory":"GENERIC","calibratedData":1},{"userProfilePK":81077219,"calendarDate":"2023-08-31","deviceId":3312246524,"updateTimestamp":"2023-08-31T15:43:17.0","sport":"WALKING","subSport":"GENERIC","vo2MaxValue":40.0,"fitnessAge":"24","fitnessAgeDescription":"2","analyzerMethod":5,"maxMet":11.43609619140625,"maxMetCategory":"GENERIC","calibratedData":1},{"userProfilePK":81077219,"calendarDate":"2023-08-31","deviceId":3312246524,"updateTimestamp":"2023-09-01T01:59:07.0","sport":"WALKING","subSport":"GENERIC","vo2MaxValue":40.0,"fitnessAge":"23","fitnessAgeDescription":"3","analyzerMethod":5,"maxMet":11.533233642578125,"maxMetCategory":"GENERIC","calibratedData":1},{"userProfilePK":81077219,"calendarDate":"2023-09-01","deviceId":3312246524,"updateTimestamp":"2023-09-01T16:57:11.0","sport":"WALKING","subSport":"GENERIC","vo2MaxValue":40.0,"fitnessAge":"23","fitnessAgeDescription":"2","analyzerMethod":5,"maxMet":11.470352172851562,"maxMetCategory":"GENERIC","calibratedData":1},{"userProfilePK":81077219,"calendarDate":"2023-09-02","deviceId":3312246524,"updateTimestamp":"2023-09-03T01:40:22.0","sport":"WALKING","subSport":"GENERIC","vo2MaxValue":40.0,"fitnessAge":"23","fitnessAgeDescription":"3","analyzerMethod":5,"maxMet":11.555191040039062,"maxMetCategory":"GENERIC","calibratedData":1},{"userProfilePK":81077219,"calendarDate":"2023-09-06","deviceId":3312246524,"updateTimestamp":"2023-09-07T02:08:13.0","sport":"WALKING","subSport":"GENERIC","vo2MaxValue":41.0,"fitnessAge":"22","fitnessAgeDescription":"3","analyzerMethod":5,"maxMet":11.661941528320312,"maxMetCategory":"GENERIC","calibratedData":1},{"userProfilePK":81077219,"calendarDate":"2023-09-07","deviceId":3312246524,"updateTimestamp":"2023-09-07T16:00:03.0","sport":"WALKING","subSport":"GENERIC","vo2MaxValue":41.0,"fitnessAge":"22","fitnessAgeDescription":"3","analyzerMethod":5,"maxMet":11.6749267578125,"maxMetCategory":"GENERIC","calibratedData":1},{"userProfilePK":81077219,"calendarDate":"2023-09-11","deviceId":3312246524,"updateTimestamp":"2023-09-12T01:56:23.0","sport":"WALKING","subSport":"GENERIC","vo2MaxValue":41.0,"fitnessAge":"22","fitnessAgeDescription":"3","analyzerMethod":5,"maxMet":11.669601440429688,"maxMetCategory":"GENERIC","calibratedData":1},{"userProfilePK":81077219,"calendarDate":"2023-09-13","deviceId":3312246524,"updateTimestamp":"2023-09-13T19:22:50.0","sport":"WALKING","subSport":"GENERIC","vo2MaxValue":41.0,"fitnessAge":"21","fitnessAgeDescription":"3","analyzerMethod":5,"maxMet":11.723007202148438,"maxMetCategory":"GENERIC","calibratedData":1},{"userProfilePK":81077219,"calendarDate":"2023-09-13","deviceId":3312246524,"updateTimestamp":"2023-09-13T20:15:48.0","sport":"WALKING","subSport":"GENERIC","vo2MaxValue":41.0,"fitnessAge":"22","fitnessAgeDescription":"3","analyzerMethod":5,"maxMet":11.620681762695312,"maxMetCategory":"GENERIC","calibratedData":1},{"userProfilePK":81077219,"calendarDate":"2023-09-13","deviceId":3312246524,"updateTimestamp":"2023-09-13T21:04:32.0","sport":"WALKING","subSport":"GENERIC","vo2MaxValue":41.0,"fitnessAge":"22","fitnessAgeDescription":"3","analyzerMethod":5,"maxMet":11.63232421875,"maxMetCategory":"GENERIC","calibratedData":1},{"userProfilePK":81077219,"calendarDate":"2023-09-14","deviceId":3312246524,"updateTimestamp":"2023-09-14T20:46:10.0","sport":"WALKING","subSport":"GENERIC","vo2MaxValue":40.0,"fitnessAge":"23","fitnessAgeDescription":"2","analyzerMethod":5,"maxMet":11.472625732421875,"maxMetCategory":"GENERIC","calibratedData":1},{"userProfilePK":81077219,"calendarDate":"2023-09-14","deviceId":3312246524,"updateTimestamp":"2023-09-14T22:08:41.0","sport":"WALKING","subSport":"GENERIC","vo2MaxValue":40.0,"fitnessAge":"24","fitnessAgeDescription":"2","analyzerMethod":5,"maxMet":11.45068359375,"maxMetCategory":"GENERIC","calibratedData":1},{"userProfilePK":81077219,"calendarDate":"2023-09-15","deviceId":3312246524,"updateTimestamp":"2023-09-15T21:59:54.0","sport":"WALKING","subSport":"GENERIC","vo2MaxValue":41.0,"fitnessAge":"22","fitnessAgeDescription":"3","analyzerMethod":5,"maxMet":11.577606201171875,"maxMetCategory":"GENERIC","calibratedData":1},{"userProfilePK":81077219,"calendarDate":"2023-09-15","deviceId":3312246524,"updateTimestamp":"2023-09-16T00:18:08.0","sport":"WALKING","subSport":"GENERIC","vo2MaxValue":41.0,"fitnessAge":"22","fitnessAgeDescription":"3","analyzerMethod":5,"maxMet":11.629119873046875,"maxMetCategory":"GENERIC","calibratedData":1},{"userProfilePK":81077219,"calendarDate":"2023-09-17","deviceId":3312246524,"updateTimestamp":"2023-09-17T16:39:35.0","sport":"WALKING","subSport":"GENERIC","vo2MaxValue":41.0,"fitnessAge":"21","fitnessAgeDescription":"3","analyzerMethod":5,"maxMet":11.710556030273438,"maxMetCategory":"GENERIC","calibratedData":1},{"userProfilePK":81077219,"calendarDate":"2023-09-17","deviceId":3312246524,"updateTimestamp":"2023-09-17T17:21:08.0","sport":"WALKING","subSport":"GENERIC","vo2MaxValue":41.0,"fitnessAge":"21","fitnessAgeDescription":"3","analyzerMethod":5,"maxMet":11.759445190429688,"maxMetCategory":"GENERIC","calibratedData":1},{"userProfilePK":81077219,"calendarDate":"2023-09-17","deviceId":3312246524,"updateTimestamp":"2023-09-17T20:53:13.0","sport":"WALKING","subSport":"GENERIC","vo2MaxValue":41.0,"fitnessAge":"22","fitnessAgeDescription":"3","analyzerMethod":5,"maxMet":11.59259033203125,"maxMetCategory":"GENERIC","calibratedData":1},{"userProfilePK":81077219,"calendarDate":"2023-09-17","deviceId":3312246524,"updateTimestamp":"2023-09-18T03:01:30.0","sport":"WALKING","subSport":"GENERIC","vo2MaxValue":41.0,"fitnessAge":"21","fitnessAgeDescription":"3","analyzerMethod":5,"maxMet":11.689376831054688,"maxMetCategory":"GENERIC","calibratedData":1},{"userProfilePK":81077219,"calendarDate":"2023-09-18","deviceId":3312246524,"updateTimestamp":"2023-09-18T16:15:47.0","sport":"WALKING","subSport":"GENERIC","vo2MaxValue":41.0,"fitnessAge":"21","fitnessAgeDescription":"3","analyzerMethod":5,"maxMet":11.73333740234375,"maxMetCategory":"GENERIC","calibratedData":1},{"userProfilePK":81077219,"calendarDate":"2023-09-18","deviceId":3312246524,"updateTimestamp":"2023-09-18T16:51:15.0","sport":"WALKING","subSport":"GENERIC","vo2MaxValue":41.0,"fitnessAge":"20","fitnessAgeDescription":"3","analyzerMethod":5,"maxMet":11.821136474609375,"maxMetCategory":"GENERIC","calibratedData":1},{"userProfilePK":81077219,"calendarDate":"2023-09-20","deviceId":3312246524,"updateTimestamp":"2023-09-20T15:14:39.0","sport":"WALKING","subSport":"GENERIC","vo2MaxValue":41.0,"fitnessAge":"20","fitnessAgeDescription":"3","analyzerMethod":5,"maxMet":11.7952880859375,"maxMetCategory":"GENERIC","calibratedData":1},{"userProfilePK":81077219,"calendarDate":"2023-09-21","deviceId":3312246524,"updateTimestamp":"2023-09-21T15:32:36.0","sport":"WALKING","subSport":"GENERIC","vo2MaxValue":41.0,"fitnessAge":"21","fitnessAgeDescription":"3","analyzerMethod":5,"maxMet":11.76898193359375,"maxMetCategory":"GENERIC","calibratedData":1},{"userProfilePK":81077219,"calendarDate":"2023-09-25","deviceId":3312246524,"updateTimestamp":"2023-09-25T23:44:03.0","sport":"WALKING","subSport":"GENERIC","vo2MaxValue":42.0,"fitnessAge":"20","fitnessAgeDescription":"3","analyzerMethod":5,"maxMet":11.93792724609375,"maxMetCategory":"GENERIC","calibratedData":1},{"userProfilePK":81077219,"calendarDate":"2023-09-26","deviceId":3312246524,"updateTimestamp":"2023-09-26T15:54:52.0","sport":"WALKING","subSport":"GENERIC","vo2MaxValue":42.0,"fitnessAge":"20","fitnessAgeDescription":"3","analyzerMethod":5,"maxMet":11.862411499023438,"maxMetCategory":"GENERIC","calibratedData":1},{"userProfilePK":81077219,"calendarDate":"2023-09-27","deviceId":3312246524,"updateTimestamp":"2023-09-27T15:49:45.0","sport":"WALKING","subSport":"GENERIC","vo2MaxValue":42.0,"fitnessAge":"20","fitnessAgeDescription":"3","analyzerMethod":5,"maxMet":11.893508911132812,"maxMetCategory":"GENERIC","calibratedData":1},{"userProfilePK":81077219,"calendarDate":"2023-09-30","deviceId":3312246524,"updateTimestamp":"2023-09-30T20:11:01.0","sport":"WALKING","subSport":"GENERIC","vo2MaxValue":42.0,"fitnessAge":"20","fitnessAgeDescription":"3","analyzerMethod":5,"maxMet":11.95379638671875,"maxMetCategory":"GENERIC","calibratedData":1},{"userProfilePK":81077219,"calendarDate":"2023-10-02","deviceId":3312246524,"updateTimestamp":"2023-10-02T15:29:49.0","sport":"WALKING","subSport":"GENERIC","vo2MaxValue":42.0,"fitnessAge":"20","fitnessAgeDescription":"3","analyzerMethod":5,"maxMet":11.975418090820312,"maxMetCategory":"GENERIC","calibratedData":1}]